{
  "label" : "Borgholzhausen",
  "assets" : {
    "Immaterielle Vermögensgegenstände und Sachanlagen" : {
      "Anlagevermögen" : [ {
        "label" : "Anlagevermoegen - Buchwert am 31.12.",
        "current" : {
          "no" : "0008",
          "value" : 53036662
        },
        "previous" : {
          "no" : "0009",
          "value" : 53036662
        }
      }, {
        "label" : "Anlagevermoegen - AHK am 31.12.",
        "current" : null,
        "previous" : {
          "no" : "0001",
          "value" : 53036662
        }
      } ],
      "Immaterielle Vermögensgegenstände" : [ {
        "label" : "Buchwert der Sachanlagen am 31.12.",
        "current" : {
          "no" : "0198",
          "value" : 43108415
        },
        "previous" : {
          "no" : "0199",
          "value" : 43108415
        }
      }, {
        "label" : "Stand der AHK der Sachanlagen am 31.12.",
        "current" : null,
        "previous" : {
          "no" : "0191",
          "value" : 43108415
        }
      } ],
      "Unbebaute Grundstücke und grundstücksgleiche Rechte" : [ {
        "label" : "Stand der AHK von Wald und Forsten am 31.12.",
        "current" : null,
        "previous" : {
          "no" : "0231",
          "value" : 62667
        }
      }, {
        "label" : "Stand der AHK von sonstigen unbebauten Grundstuecken am 31.12.",
        "current" : null,
        "previous" : {
          "no" : "0241",
          "value" : 706890
        }
      }, {
        "label" : "Buchwert der Gruenflaechen am 31.12.",
        "current" : {
          "no" : "0218",
          "value" : 1888631
        },
        "previous" : {
          "no" : "0219",
          "value" : 1888631
        }
      }, {
        "label" : "Stand der AHK der unbebauten Grundstuecke und grundstuecksgleichen Rechte am 31.12.",
        "current" : null,
        "previous" : {
          "no" : "0201",
          "value" : 3390041
        }
      }, {
        "label" : "Buchwert der unbebauten Grundstuecke und grundstuecksgleichen Rechte am 31.12.",
        "current" : {
          "no" : "0208",
          "value" : 3390041
        },
        "previous" : {
          "no" : "0209",
          "value" : 3390041
        }
      }, {
        "label" : "Stand der AHK von Gruenflaechen am 31.12.",
        "current" : null,
        "previous" : {
          "no" : "0211",
          "value" : 1888631
        }
      }, {
        "label" : "Buchwert des Ackerlandes am 31.12.",
        "current" : {
          "no" : "0228",
          "value" : 731853
        },
        "previous" : {
          "no" : "0229",
          "value" : 731853
        }
      }, {
        "label" : "Stand der AHK von Ackerland am 31.12.",
        "current" : null,
        "previous" : {
          "no" : "0221",
          "value" : 731853
        }
      }, {
        "label" : "Buchwert des Waldes und der Forsten am 31.12.",
        "current" : {
          "no" : "0238",
          "value" : 62667
        },
        "previous" : {
          "no" : "0239",
          "value" : 62667
        }
      }, {
        "label" : "Buchwert der sonstigen unbebauten Grundstuecke am 31.12.",
        "current" : {
          "no" : "0248",
          "value" : 706890
        },
        "previous" : {
          "no" : "0249",
          "value" : 706890
        }
      } ],
      "Bebaute Grundstücke und grundstücksgleiche Rechte" : [ {
        "label" : "Buchwert der Wohnbauten am 31.12.",
        "current" : {
          "no" : "0338",
          "value" : 970000
        },
        "previous" : {
          "no" : "0339",
          "value" : 970000
        }
      }, {
        "label" : "Buchwert der bebauten Grundstuecke und grundstuecksgleichen Rechte am 31.12.",
        "current" : {
          "no" : "0308",
          "value" : 13887794
        },
        "previous" : {
          "no" : "0309",
          "value" : 13887794
        }
      }, {
        "label" : "Buchwert der sonstigen Gebaeude am 31.12.",
        "current" : {
          "no" : "0398",
          "value" : 12569089
        },
        "previous" : {
          "no" : "0399",
          "value" : 12569089
        }
      }, {
        "label" : "Stand der AHK von sonstigen Gebaeuden am 31.12.",
        "current" : null,
        "previous" : {
          "no" : "0391",
          "value" : 12569089
        }
      }, {
        "label" : "Stand der AHK von Schulen am 31.12.",
        "current" : null,
        "previous" : {
          "no" : "0321",
          "value" : 348705
        }
      }, {
        "label" : "Buchwert der Schulen am 31.12.",
        "current" : {
          "no" : "0328",
          "value" : 348705
        },
        "previous" : {
          "no" : "0329",
          "value" : 348705
        }
      }, {
        "label" : "Stand der AHK der bebauten Grundstuecke und grundstuecksgleichen Rechte am 31.12.",
        "current" : null,
        "previous" : {
          "no" : "0301",
          "value" : 13887794
        }
      }, {
        "label" : "Stand der AHK von Wohnbauten am 31.12.",
        "current" : null,
        "previous" : {
          "no" : "0331",
          "value" : 970000
        }
      } ],
      "Infrastrukturvermögen" : [ {
        "label" : "Stand der AHK des Infrastrukturvermoegens am 31.12.",
        "current" : null,
        "previous" : {
          "no" : "0401",
          "value" : 24976969
        }
      }, {
        "label" : "Buchwert des Straßennetzes am 31.12.",
        "current" : {
          "no" : "0458",
          "value" : 20633298
        },
        "previous" : {
          "no" : "0459",
          "value" : 20633298
        }
      }, {
        "label" : "Buchwert der Infrastrukturgrundstuecke am 31.12.",
        "current" : {
          "no" : "0418",
          "value" : 4343671
        },
        "previous" : {
          "no" : "0419",
          "value" : 4343671
        }
      }, {
        "label" : "Buchwert des Infrastrukturvermoegens am 31.12.",
        "current" : {
          "no" : "0408",
          "value" : 24976969
        },
        "previous" : {
          "no" : "0409",
          "value" : 24976969
        }
      }, {
        "label" : "Stand der AHK des Straßennetzes am 31.12.",
        "current" : null,
        "previous" : {
          "no" : "0451",
          "value" : 20633298
        }
      }, {
        "label" : "Stand der AHK von Infrastrukturgrundstuecken am 31.12.",
        "current" : null,
        "previous" : {
          "no" : "0411",
          "value" : 4343671
        }
      } ],
      "Bauten auf fremdem Grund und Boden" : [ ],
      "Kunstgegenstände, Kulturdenkmäler" : [ ],
      "Maschinen und technische Anlagen, Fahrzeuge" : [ {
        "label" : "Stand der AHK der technischen Ausstattung am 31.12.",
        "current" : null,
        "previous" : {
          "no" : "0711",
          "value" : 476907
        }
      }, {
        "label" : "Buchwert der technischen Ausstattung am 31.12.",
        "current" : {
          "no" : "0718",
          "value" : 476907
        },
        "previous" : {
          "no" : "0719",
          "value" : 476907
        }
      } ],
      "Betriebs- und Geschäftsausstattung" : [ {
        "label" : "Stand der AHK der Betriebs- und Geschaeftsausstattung am 31.12.",
        "current" : null,
        "previous" : {
          "no" : "0811",
          "value" : 376704
        }
      }, {
        "label" : "Buchwert der Betriebs- und Geschaeftsausstattung am 31.12.",
        "current" : {
          "no" : "0818",
          "value" : 376704
        },
        "previous" : {
          "no" : "0819",
          "value" : 376704
        }
      } ],
      "Geleistete Anzahlungen, Anlagen im Bau" : [ ],
      "Anteile an verbundenen Unternehmen" : [ ],
      "Beteiligungen" : [ ],
      "Sondervermögen" : [ ],
      "Ausleihungen" : [ ],
      "Wertpapiere" : [ ],
      "Vorräte" : [ ],
      "Öffentlich-rechtliche Forderungen und Forderungen aus Transferleistungen" : [ ],
      "Privatrechtliche Forderungen, sonstige Vermögensgegenstände" : [ ],
      "Liquide Mittel" : [ ],
      "Aktive Rechnungsabgrenzung" : [ ],
      "Eigenkapital" : [ ],
      "Wertberichtigungen (kein Bilanzausweis)" : [ ],
      "Sonderposten" : [ ],
      "Pensionsrückstellungen" : [ ],
      "Rückstellungen für Deponien und Altlasten" : [ ],
      "Instandhaltungsrückstellungen" : [ ],
      "Sonstige Rückstellungen" : [ ],
      "Anleihen" : [ ],
      "Verbindlichkeiten aus Krediten für Investitionen" : [ ],
      "Verbindlichkeiten aus Krediten zur Liquiditätssicherung" : [ ],
      "Verbindlichkeiten aus Vorgängen, die Kreditaufnahmen wirtschaftlich gleichkommen" : [ ],
      "Verbindlichkeiten aus Lieferungen und Leistungen" : [ ],
      "Verbindlichkeiten aus Transferleistungen" : [ ],
      "Sonstige Verbindlichkeiten" : [ ],
      "Passive Rechnungsabgrenzung" : [ ]
    },
    "Finanzanlagen, Umlaufvermögen und aktive Rechnungsabgrenzung" : {
      "Anlagevermögen" : [ ],
      "Immaterielle Vermögensgegenstände" : [ ],
      "Unbebaute Grundstücke und grundstücksgleiche Rechte" : [ ],
      "Bebaute Grundstücke und grundstücksgleiche Rechte" : [ ],
      "Infrastrukturvermögen" : [ ],
      "Bauten auf fremdem Grund und Boden" : [ ],
      "Kunstgegenstände, Kulturdenkmäler" : [ ],
      "Maschinen und technische Anlagen, Fahrzeuge" : [ ],
      "Betriebs- und Geschäftsausstattung" : [ ],
      "Geleistete Anzahlungen, Anlagen im Bau" : [ ],
      "Anteile an verbundenen Unternehmen" : [ {
        "label" : "Buchwert der Finanzanlagen am 31.12.",
        "current" : {
          "no" : "1008",
          "value" : 9928247
        },
        "previous" : {
          "no" : "1009",
          "value" : 9928247
        }
      }, {
        "label" : "Stand der AHK der Finanzanlagen am 31.12.",
        "current" : null,
        "previous" : {
          "no" : "1001",
          "value" : 9928247
        }
      } ],
      "Beteiligungen" : [ {
        "label" : "Buchwert der Beteiligungen am 31.12.",
        "current" : {
          "no" : "1118",
          "value" : 9983
        },
        "previous" : {
          "no" : "1119",
          "value" : 9983
        }
      }, {
        "label" : "Stand der AHK von Beteiligungen am 31.12.",
        "current" : null,
        "previous" : {
          "no" : "1111",
          "value" : 9983
        }
      } ],
      "Sondervermögen" : [ {
        "label" : "Buchwert der Sondervermoegen am 31.12.",
        "current" : {
          "no" : "1218",
          "value" : 9866038
        },
        "previous" : {
          "no" : "1219",
          "value" : 9866038
        }
      }, {
        "label" : "Stand der AHK von Sondervermoegen am 31.12.",
        "current" : null,
        "previous" : {
          "no" : "1211",
          "value" : 9866038
        }
      } ],
      "Ausleihungen" : [ ],
      "Wertpapiere" : [ {
        "label" : "Buchwert des Umlaufvermoegens am 31.12.",
        "current" : {
          "no" : "1460",
          "value" : 6755080
        },
        "previous" : null
      }, {
        "label" : "Stand der AHK von Wertpapieren des Anlagevermoegens am 31.12.",
        "current" : null,
        "previous" : {
          "no" : "1411",
          "value" : 52226
        }
      }, {
        "label" : "Buchwert der Wertpapiere des Anlagevermoegens am 31.12.",
        "current" : {
          "no" : "1418",
          "value" : 52226
        },
        "previous" : {
          "no" : "1419",
          "value" : 52226
        }
      } ],
      "Vorräte" : [ ],
      "Öffentlich-rechtliche Forderungen und Forderungen aus Transferleistungen" : [ {
        "label" : "Gesamtbetrag der sonstigen oeffentlich-rechtlichen Forderungen am 31.12.",
        "current" : {
          "no" : "1651",
          "value" : 4261
        },
        "previous" : {
          "no" : "1655",
          "value" : 4261
        }
      }, {
        "label" : "Gesamtbetrag der Steuerforderungen am 31.12.",
        "current" : {
          "no" : "1631",
          "value" : 438356
        },
        "previous" : {
          "no" : "1635",
          "value" : 438356
        }
      }, {
        "label" : "Sonstige oeffentlich-rechtliche Forderungen mit einer Restlaufzeit von bis zu 1 Jahr",
        "current" : {
          "no" : "1652",
          "value" : 4261
        },
        "previous" : null
      }, {
        "label" : "Gesamtbetrag der Gebuehrenforderungen am 31.12.",
        "current" : {
          "no" : "1611",
          "value" : 13120
        },
        "previous" : {
          "no" : "1615",
          "value" : 13120
        }
      }, {
        "label" : "Forderungen mit einer Restlaufzeit von bis zu 1 Jahr",
        "current" : {
          "no" : "1602",
          "value" : 754857
        },
        "previous" : null
      }, {
        "label" : "Beitragsforderungen mit einer Restlaufzeit von bis zu 1 Jahr",
        "current" : {
          "no" : "1622",
          "value" : 19428
        },
        "previous" : null
      }, {
        "label" : "Gesamtbetrag der oeffentlich-rechtlichen Forderungen am 31.12.",
        "current" : {
          "no" : "1606",
          "value" : 475165
        },
        "previous" : {
          "no" : "1610",
          "value" : 475165
        }
      }, {
        "label" : "Gesamtbetrag der Forderungen am 31.12.",
        "current" : {
          "no" : "1601",
          "value" : 1021470
        },
        "previous" : {
          "no" : "1605",
          "value" : 1021470
        }
      }, {
        "label" : "Forderungen mit einer Restlaufzeit von 1 bis 5 Jahren",
        "current" : {
          "no" : "1603",
          "value" : 38528
        },
        "previous" : null
      }, {
        "label" : "oeffentlich-rechtliche Forderungen mit einer Restlaufzeit von bis zu 1 Jahr",
        "current" : {
          "no" : "1607",
          "value" : 474792
        },
        "previous" : null
      }, {
        "label" : "oeffentlich-rechtliche Forderungen mit einer Restlaufzeit von 1 bis 5 Jahren",
        "current" : {
          "no" : "1608",
          "value" : 373
        },
        "previous" : null
      }, {
        "label" : "Gebuehrenforderungen mit einer Restlaufzeit von bis zu 1 Jahr",
        "current" : {
          "no" : "1612",
          "value" : 13120
        },
        "previous" : null
      }, {
        "label" : "Steuerforderungen mit einer Restlaufzeit von 1 bis 5 Jahren",
        "current" : {
          "no" : "1633",
          "value" : 373
        },
        "previous" : null
      }, {
        "label" : "Steuerforderungen mit einer Restlaufzeit von bis zu 1 Jahr",
        "current" : {
          "no" : "1632",
          "value" : 437983
        },
        "previous" : null
      }, {
        "label" : "Gesamtbetrag der Beitragsforderungen am 31.12.",
        "current" : {
          "no" : "1621",
          "value" : 19428
        },
        "previous" : {
          "no" : "1625",
          "value" : 19428
        }
      }, {
        "label" : "Forderungen mit einer Restlaufzeit von mehr als 5 Jahren",
        "current" : {
          "no" : "1604",
          "value" : 228085
        },
        "previous" : null
      } ],
      "Privatrechtliche Forderungen, sonstige Vermögensgegenstände" : [ {
        "label" : "Gesamtbetrag der privatrechtlichen Forderungen am 31.12.",
        "current" : {
          "no" : "1706",
          "value" : 546305
        },
        "previous" : {
          "no" : "1710",
          "value" : 546305
        }
      }, {
        "label" : "Privatrechtliche Forderungen gegenueber dem priv. Bereich mit einer Restlaufzeit von bis zu 1 Jahr",
        "current" : {
          "no" : "1712",
          "value" : 20065
        },
        "previous" : null
      }, {
        "label" : "Privatrechtliche Forderungen gegenueber verbundenen Unternehmen mit einer Restlaufzeit von bis zu 1 Jahr",
        "current" : {
          "no" : "1732",
          "value" : 260000
        },
        "previous" : null
      }, {
        "label" : "Gesamtbetrag der privatrechtlichen Forderungen gegenueber dem privaten Bereich am 31.12. des Haushaltsj.",
        "current" : {
          "no" : "1711",
          "value" : 286305
        },
        "previous" : null
      }, {
        "label" : "Privatrechtliche Forderungen mit einer Restlaufzeit von mehr als 5 Jahren",
        "current" : {
          "no" : "1709",
          "value" : 228085
        },
        "previous" : null
      }, {
        "label" : "Gesamtbetrag der privatrechtlichen Forderungen gegenueber verbundenen Unternehmen am 31.12. des Haushaltsj.",
        "current" : {
          "no" : "1731",
          "value" : 260000
        },
        "previous" : null
      }, {
        "label" : "Gesamtbetrag der privatrechtlichen Forderungen gegenueber verbundenen Unternehmen am 31.12.",
        "current" : null,
        "previous" : {
          "no" : "1735",
          "value" : 260000
        }
      }, {
        "label" : "Privatrechtliche Forderungen mit einer Restlaufzeit von bis zu 1 Jahr",
        "current" : {
          "no" : "1707",
          "value" : 280065
        },
        "previous" : null
      }, {
        "label" : "Privatrechtliche Forderungen gegenueber dem priv. Bereich mit einer Restlaufzeit von 1 bis 5 Jahren",
        "current" : {
          "no" : "1713",
          "value" : 38155
        },
        "previous" : null
      }, {
        "label" : "Privatrechtliche Forderungen gegenueber dem priv. Bereich mit einer Restlaufzeit von mehr als 5 Jahren",
        "current" : {
          "no" : "1714",
          "value" : 228085
        },
        "previous" : null
      }, {
        "label" : "Gesamtbetrag der privatrechtlichen Forderungen gegenueber dem priv. Bereich am 31.12.",
        "current" : null,
        "previous" : {
          "no" : "1715",
          "value" : 286305
        }
      }, {
        "label" : "Privatrechtliche Forderungen mit einer Restlaufzeit von 1 bis 5 Jahren",
        "current" : {
          "no" : "1708",
          "value" : 38155
        },
        "previous" : null
      } ],
      "Liquide Mittel" : [ {
        "label" : "Liquide Mittel",
        "current" : {
          "no" : "1891",
          "value" : 5733610
        },
        "previous" : null
      } ],
      "Aktive Rechnungsabgrenzung" : [ ],
      "Eigenkapital" : [ ],
      "Wertberichtigungen (kein Bilanzausweis)" : [ ],
      "Sonderposten" : [ ],
      "Pensionsrückstellungen" : [ ],
      "Rückstellungen für Deponien und Altlasten" : [ ],
      "Instandhaltungsrückstellungen" : [ ],
      "Sonstige Rückstellungen" : [ ],
      "Anleihen" : [ ],
      "Verbindlichkeiten aus Krediten für Investitionen" : [ ],
      "Verbindlichkeiten aus Krediten zur Liquiditätssicherung" : [ ],
      "Verbindlichkeiten aus Vorgängen, die Kreditaufnahmen wirtschaftlich gleichkommen" : [ ],
      "Verbindlichkeiten aus Lieferungen und Leistungen" : [ ],
      "Verbindlichkeiten aus Transferleistungen" : [ ],
      "Sonstige Verbindlichkeiten" : [ ],
      "Passive Rechnungsabgrenzung" : [ ]
    }
  },
  "liabilities" : {
    "Eigenkapital, Sonderposten und Rückstellungen" : {
      "Anlagevermögen" : [ ],
      "Immaterielle Vermögensgegenstände" : [ ],
      "Unbebaute Grundstücke und grundstücksgleiche Rechte" : [ ],
      "Bebaute Grundstücke und grundstücksgleiche Rechte" : [ ],
      "Infrastrukturvermögen" : [ ],
      "Bauten auf fremdem Grund und Boden" : [ ],
      "Kunstgegenstände, Kulturdenkmäler" : [ ],
      "Maschinen und technische Anlagen, Fahrzeuge" : [ ],
      "Betriebs- und Geschäftsausstattung" : [ ],
      "Geleistete Anzahlungen, Anlagen im Bau" : [ ],
      "Anteile an verbundenen Unternehmen" : [ ],
      "Beteiligungen" : [ ],
      "Sondervermögen" : [ ],
      "Ausleihungen" : [ ],
      "Wertpapiere" : [ ],
      "Vorräte" : [ ],
      "Öffentlich-rechtliche Forderungen und Forderungen aus Transferleistungen" : [ ],
      "Privatrechtliche Forderungen, sonstige Vermögensgegenstände" : [ ],
      "Liquide Mittel" : [ ],
      "Aktive Rechnungsabgrenzung" : [ ],
      "Eigenkapital" : [ {
        "label" : "Allgemeine Ruecklage",
        "current" : {
          "no" : "2011",
          "value" : 31540438
        },
        "previous" : null
      }, {
        "label" : "Ausgleichsruecklage",
        "current" : {
          "no" : "2041",
          "value" : 4170000
        },
        "previous" : null
      }, {
        "label" : "Eigenkapital",
        "current" : {
          "no" : "2001",
          "value" : 35710438
        },
        "previous" : null
      } ],
      "Wertberichtigungen (kein Bilanzausweis)" : [ ],
      "Sonderposten" : [ {
        "label" : "Sonstige Sonderposten",
        "current" : {
          "no" : "2391",
          "value" : 6201524
        },
        "previous" : null
      }, {
        "label" : "Sonderposten aus Zuwendungen",
        "current" : {
          "no" : "2311",
          "value" : 5251425
        },
        "previous" : null
      }, {
        "label" : "Sonderposten aus Beitraegen",
        "current" : {
          "no" : "2321",
          "value" : 3647447
        },
        "previous" : null
      }, {
        "label" : "Sonderposten",
        "current" : {
          "no" : "2301",
          "value" : 15119288
        },
        "previous" : null
      }, {
        "label" : "Sonderposten fuer den Gebuehrenausgleich",
        "current" : {
          "no" : "2331",
          "value" : 18892
        },
        "previous" : null
      } ],
      "Pensionsrückstellungen" : [ {
        "label" : "Pensionsrueckstellungen",
        "current" : {
          "no" : "2511",
          "value" : 3919851
        },
        "previous" : null
      }, {
        "label" : "Rueckstellungen",
        "current" : {
          "no" : "2501",
          "value" : 5206968
        },
        "previous" : null
      } ],
      "Rückstellungen für Deponien und Altlasten" : [ ],
      "Instandhaltungsrückstellungen" : [ {
        "label" : "Instandhaltungsrueckstellungen",
        "current" : {
          "no" : "2711",
          "value" : 112000
        },
        "previous" : null
      } ],
      "Sonstige Rückstellungen" : [ {
        "label" : "Sonstige Rueckstellungen",
        "current" : {
          "no" : "2811",
          "value" : 1175117
        },
        "previous" : null
      } ],
      "Anleihen" : [ ],
      "Verbindlichkeiten aus Krediten für Investitionen" : [ ],
      "Verbindlichkeiten aus Krediten zur Liquiditätssicherung" : [ ],
      "Verbindlichkeiten aus Vorgängen, die Kreditaufnahmen wirtschaftlich gleichkommen" : [ ],
      "Verbindlichkeiten aus Lieferungen und Leistungen" : [ ],
      "Verbindlichkeiten aus Transferleistungen" : [ ],
      "Sonstige Verbindlichkeiten" : [ ],
      "Passive Rechnungsabgrenzung" : [ ]
    },
    "Verbindlichkeiten und passive Rechnungsabgrenzung" : {
      "Anlagevermögen" : [ ],
      "Immaterielle Vermögensgegenstände" : [ ],
      "Unbebaute Grundstücke und grundstücksgleiche Rechte" : [ ],
      "Bebaute Grundstücke und grundstücksgleiche Rechte" : [ ],
      "Infrastrukturvermögen" : [ ],
      "Bauten auf fremdem Grund und Boden" : [ ],
      "Kunstgegenstände, Kulturdenkmäler" : [ ],
      "Maschinen und technische Anlagen, Fahrzeuge" : [ ],
      "Betriebs- und Geschäftsausstattung" : [ ],
      "Geleistete Anzahlungen, Anlagen im Bau" : [ ],
      "Anteile an verbundenen Unternehmen" : [ ],
      "Beteiligungen" : [ ],
      "Sondervermögen" : [ ],
      "Ausleihungen" : [ ],
      "Wertpapiere" : [ ],
      "Vorräte" : [ ],
      "Öffentlich-rechtliche Forderungen und Forderungen aus Transferleistungen" : [ ],
      "Privatrechtliche Forderungen, sonstige Vermögensgegenstände" : [ ],
      "Liquide Mittel" : [ ],
      "Aktive Rechnungsabgrenzung" : [ ],
      "Eigenkapital" : [ ],
      "Wertberichtigungen (kein Bilanzausweis)" : [ ],
      "Sonderposten" : [ ],
      "Pensionsrückstellungen" : [ ],
      "Rückstellungen für Deponien und Altlasten" : [ ],
      "Instandhaltungsrückstellungen" : [ ],
      "Sonstige Rückstellungen" : [ ],
      "Anleihen" : [ {
        "label" : "Verbindlichkeiten mit einer Restlaufzeit von bis zu 1 Jahr",
        "current" : {
          "no" : "3002",
          "value" : 426714
        },
        "previous" : null
      }, {
        "label" : "Gesamtbetrag der Verbindlichkeiten am 31.12.",
        "current" : {
          "no" : "3001",
          "value" : 3755048
        },
        "previous" : {
          "no" : "3005",
          "value" : 3755048
        }
      }, {
        "label" : "Verbindlichkeiten mit einer Restlaufzeit von 1 bis 5 Jahren",
        "current" : {
          "no" : "3003",
          "value" : 1043124
        },
        "previous" : null
      }, {
        "label" : "Verbindlichkeiten mit einer Restlaufzeit von mehr als 5 Jahren",
        "current" : {
          "no" : "3004",
          "value" : 2285210
        },
        "previous" : null
      } ],
      "Verbindlichkeiten aus Krediten für Investitionen" : [ {
        "label" : "Investitionskredite vom Kreditmarkt mit einer Restlaufzeit von mehr als 5 Jahren",
        "current" : {
          "no" : "32504",
          "value" : 2285210
        },
        "previous" : null
      }, {
        "label" : "Gesamtbetrag der Investitionskredite am 31.12.",
        "current" : {
          "no" : "3201",
          "value" : 3733321
        },
        "previous" : {
          "no" : "3205",
          "value" : 3733321
        }
      }, {
        "label" : "Investitionskredite mit einer Restlaufzeit von bis zu 1 Jahr",
        "current" : {
          "no" : "3202",
          "value" : 404987
        },
        "previous" : null
      }, {
        "label" : "Investitionskredite vom Kreditmarkt mit einer Restlaufzeit von 1 bis 5 Jahren",
        "current" : {
          "no" : "32503",
          "value" : 1043124
        },
        "previous" : null
      }, {
        "label" : "Investitionskredite vom Kreditmarkt mit einer Restlaufzeit von bis zu 1 Jahr",
        "current" : {
          "no" : "32502",
          "value" : 404987
        },
        "previous" : null
      }, {
        "label" : "Investitionskredite von Banken und Kreditinstituten mit einer Restlaufzeit von mehr als 5 Jahren",
        "current" : {
          "no" : "32514",
          "value" : 2285210
        },
        "previous" : null
      }, {
        "label" : "Investitionskredite mit einer Restlaufzeit von mehr als 5 Jahren",
        "current" : {
          "no" : "3204",
          "value" : 2285210
        },
        "previous" : null
      }, {
        "label" : "Investitionskredite von Banken und Kreditinstituten mit einer Restlaufzeit von bis zu 1 Jahr",
        "current" : {
          "no" : "32512",
          "value" : 404987
        },
        "previous" : null
      }, {
        "label" : "Gesamtbetrag der Investitionskredite vom Kreditmarkt am 31.12.",
        "current" : {
          "no" : "32501",
          "value" : 3733321
        },
        "previous" : {
          "no" : "32505",
          "value" : 3733321
        }
      }, {
        "label" : "Investitionskredite von Banken und Kreditinstituten mit einer Restlaufzeit von 1 bis 5 Jahren",
        "current" : {
          "no" : "32513",
          "value" : 1043124
        },
        "previous" : null
      }, {
        "label" : "Gesamtbetrag der Investitionskredite von Banken und Kreditinstituten am 31.12.",
        "current" : {
          "no" : "32511",
          "value" : 3733321
        },
        "previous" : {
          "no" : "32515",
          "value" : 3733321
        }
      }, {
        "label" : "Investitionskredite mit einer Restlaufzeit von 1 bis 5 Jahren",
        "current" : {
          "no" : "3203",
          "value" : 1043124
        },
        "previous" : null
      } ],
      "Verbindlichkeiten aus Krediten zur Liquiditätssicherung" : [ ],
      "Verbindlichkeiten aus Vorgängen, die Kreditaufnahmen wirtschaftlich gleichkommen" : [ ],
      "Verbindlichkeiten aus Lieferungen und Leistungen" : [ {
        "label" : "Verbindlichkeiten aus Lieferungen und Leistungen mit einer Restlaufzeit von bis zu 1 Jahr",
        "current" : {
          "no" : "3512",
          "value" : 1949
        },
        "previous" : null
      }, {
        "label" : "Gesamtbetrag der Verbindlichkeiten aus Lieferungen und Leistungen am 31.12.",
        "current" : {
          "no" : "3511",
          "value" : 1949
        },
        "previous" : {
          "no" : "3515",
          "value" : 1949
        }
      } ],
      "Verbindlichkeiten aus Transferleistungen" : [ ],
      "Sonstige Verbindlichkeiten" : [ {
        "label" : "Gesamtbetrag der sonstigen Verbindlichkeiten am 31.12.",
        "current" : {
          "no" : "3711",
          "value" : 19778
        },
        "previous" : {
          "no" : "3715",
          "value" : 19778
        }
      }, {
        "label" : "Sonstige Verbindlichkeiten mit einer Restlaufzeit von bis zu 1 Jahr",
        "current" : {
          "no" : "3712",
          "value" : 19778
        },
        "previous" : null
      } ],
      "Passive Rechnungsabgrenzung" : [ {
        "label" : "Summe Passiva",
        "current" : {
          "no" : "3998",
          "value" : 59791742
        },
        "previous" : null
      }, {
        "label" : "nachrichtlich: Summe Aktiva",
        "current" : {
          "no" : "3999",
          "value" : 59791742
        },
        "previous" : null
      } ]
    }
  }
}